odoo10_addon_crm_lead_partner_role-10.0.1.0.0.99.dev5-py3.8-nspkg.pth
odoo/addons/crm_lead_partner_role/README.rst
odoo/addons/crm_lead_partner_role/__init__.py
odoo/addons/crm_lead_partner_role/__manifest__.py
odoo/addons/crm_lead_partner_role/i18n/crm_lead_partner_role.pot
odoo/addons/crm_lead_partner_role/models/__init__.py
odoo/addons/crm_lead_partner_role/models/crm_lead.py
odoo/addons/crm_lead_partner_role/models/crm_partner_role.py
odoo/addons/crm_lead_partner_role/models/crm_role.py
odoo/addons/crm_lead_partner_role/readme/CONTRIBUTORS.rst
odoo/addons/crm_lead_partner_role/readme/DESCRIPTION.rst
odoo/addons/crm_lead_partner_role/security/ir.model.access.csv
odoo/addons/crm_lead_partner_role/static/description/icon.png
odoo/addons/crm_lead_partner_role/static/description/index.html
odoo/addons/crm_lead_partner_role/views/crm_lead.xml
odoo/addons/crm_lead_partner_role/views/crm_role.xml
odoo10_addon_crm_lead_partner_role-10.0.1.0.0.99.dev5.dist-info/METADATA
odoo10_addon_crm_lead_partner_role-10.0.1.0.0.99.dev5.dist-info/WHEEL
odoo10_addon_crm_lead_partner_role-10.0.1.0.0.99.dev5.dist-info/namespace_packages.txt
odoo10_addon_crm_lead_partner_role-10.0.1.0.0.99.dev5.dist-info/top_level.txt
odoo10_addon_crm_lead_partner_role-10.0.1.0.0.99.dev5.dist-info/RECORD
